patchouli.py
patchouli-0.1.2.dist-info/DESCRIPTION.rst
patchouli-0.1.2.dist-info/entry_points.txt
patchouli-0.1.2.dist-info/METADATA
patchouli-0.1.2.dist-info/metadata.json
patchouli-0.1.2.dist-info/RECORD
patchouli-0.1.2.dist-info/top_level.txt
patchouli-0.1.2.dist-info/WHEEL
