Metadata-Version: 2.0
Name: patchouli
Version: 0.1.2
Summary: Interactive patch file splitting tool
Home-page: https://github.com/rix0rrr/patchouli
Author: Rico Huijbers
Author-email: rix0rrr@gmail.com
License: MIT
Keywords: patch
Platform: UNKNOWN
Classifier: Development Status :: 3 - Alpha
Classifier: Intended Audience :: Developers
Classifier: Topic :: Software Development :: Version Control
Classifier: License :: OSI Approved :: MIT License
Classifier: Programming Language :: Python :: 2
Classifier: Programming Language :: Python :: 2.6
Classifier: Programming Language :: Python :: 2.7
Classifier: Programming Language :: Python :: 3
Classifier: Programming Language :: Python :: 3.2
Classifier: Programming Language :: Python :: 3.3
Classifier: Programming Language :: Python :: 3.4
Requires-Dist: unidiff (>=0.5.1)
Requires-Dist: termcolor (>=1.1.0)
